[{"date":"2026-06-25","home_team":"United States","away_team":"Turkey","home_advantage":true,"p_home":0.5233074929,"p_draw":0.2367019262,"p_away":0.239990581,"most_likely":"1:1","p_most_likely":0.1118747594},{"date":"2026-06-25","home_team":"Paraguay","away_team":"Australia","home_advantage":false,"p_home":0.2084333658,"p_draw":0.2507030585,"p_away":0.5408635757,"most_likely":"0:1","p_most_likely":0.133464087},{"date":"2026-06-25","home_team":"Cura\u00e7ao","away_team":"Ivory Coast","home_advantage":false,"p_home":0.1326923891,"p_draw":0.2084842166,"p_away":0.6588233943,"most_likely":"0:1","p_most_likely":0.1346197216},{"date":"2026-06-25","home_team":"Ecuador","away_team":"Germany","home_advantage":false,"p_home":0.3213517584,"p_draw":0.2765578607,"p_away":0.4020903809,"most_likely":"1:1","p_most_likely":0.1303544315},{"date":"2026-06-25","home_team":"Japan","away_team":"Sweden","home_advantage":false,"p_home":0.5167968918,"p_draw":0.2571921459,"p_away":0.2260109623,"most_likely":"1:0","p_most_likely":0.1317420372},{"date":"2026-06-25","home_team":"Tunisia","away_team":"Netherlands","home_advantage":false,"p_home":0.0845699646,"p_draw":0.1648547689,"p_away":0.7505752665,"most_likely":"0:2","p_most_likely":0.1430740364}]