[{"date":"2026-06-15","home_team":"Belgium","away_team":"Egypt","home_advantage":false,"p_home":0.5389082347,"p_draw":0.2512589138,"p_away":0.2098328515,"most_likely":"1:0","p_most_likely":0.1333415274},{"date":"2026-06-15","home_team":"Iran","away_team":"New Zealand","home_advantage":false,"p_home":0.5583600363,"p_draw":0.2455092337,"p_away":0.19613073,"most_likely":"1:0","p_most_likely":0.134420725},{"date":"2026-06-15","home_team":"Spain","away_team":"Cape Verde","home_advantage":false,"p_home":0.9005122849,"p_draw":0.0747937877,"p_away":0.0246939274,"most_likely":"3:0","p_most_likely":0.1437606163},{"date":"2026-06-15","home_team":"Saudi Arabia","away_team":"Uruguay","home_advantage":false,"p_home":0.1248094672,"p_draw":0.2024404431,"p_away":0.6727500897,"most_likely":"0:1","p_most_likely":0.133861345}]