[{"date":"2026-06-20","home_team":"Germany","away_team":"Ivory Coast","home_advantage":false,"p_home":0.5350623027,"p_draw":0.2523375999,"p_away":0.2126000974,"most_likely":"1:0","p_most_likely":0.1330914164},{"date":"2026-06-20","home_team":"Ecuador","away_team":"Cura\u00e7ao","home_advantage":false,"p_home":0.7767824182,"p_draw":0.1507825364,"p_away":0.0724350454,"most_likely":"2:0","p_most_likely":0.1450224485},{"date":"2026-06-20","home_team":"Netherlands","away_team":"Sweden","home_advantage":false,"p_home":0.5348395396,"p_draw":0.2523994833,"p_away":0.212760977,"most_likely":"1:0","p_most_likely":0.1330765632},{"date":"2026-06-20","home_team":"Tunisia","away_team":"Japan","home_advantage":false,"p_home":0.0919852161,"p_draw":0.1727494852,"p_away":0.7352652987,"most_likely":"0:2","p_most_likely":0.1415122194}]